krane/__init__.py
krane/cli/__init__.py
krane/cli/commands.py
krane/core/__init__.py
krane/core/models.py
krane/core/sequence.py
krane/core/utils.py
krane/web/__init__.py
krane/web/app.py
krane/web/documentation.md
krane/web/index.md
krane/web/routes/__init__.py
krane/web/routes/sequence.py
krane/web/routes/utils.py
krane/web/schemas/__init__.py
krane/web/schemas/sequence.py
krane/web/static/css/app.css
krane/web/static/css/demo.css
krane/web/static/css/help.css
krane/web/static/css/style.css
krane/web/static/img/Nodes.jpeg
krane/web/static/img/dna.svg
krane/web/static/img/favicon-16x16.png
krane/web/static/img/favicon.ico
krane/web/static/img/krane.gif
krane/web/static/img/krane.png
krane/web/static/img/krane.svg
krane/web/static/img/icons/android-chrome-192x192.png
krane/web/static/img/icons/android-chrome-512x512.png
krane/web/static/img/icons/android-chrome-maskable-192x192.png
krane/web/static/img/icons/android-chrome-maskable-512x512.png
krane/web/static/img/icons/apple-touch-icon-120x120.png
krane/web/static/img/icons/apple-touch-icon-152x152.png
krane/web/static/img/icons/apple-touch-icon-180x180.png
krane/web/static/img/icons/apple-touch-icon-60x60.png
krane/web/static/img/icons/apple-touch-icon-76x76.png
krane/web/static/img/icons/apple-touch-icon.png
krane/web/static/img/icons/favicon-16x16.png
krane/web/static/img/icons/favicon-32x32.png
krane/web/static/img/icons/msapplication-icon-144x144.png
krane/web/static/img/icons/mstile-150x150.png
krane/web/static/img/icons/safari-pinned-tab.svg
krane/web/static/js/app.js
krane/web/static/js/demo.js
krane/web/static/js/help.js
krane/web/static/js/script.js
krane/web/templates/demo.html
krane/web/templates/help.html
krane/web/templates/index.html
krane-0.1.2.dist-info/LICENSE
krane-0.1.2.dist-info/METADATA
krane-0.1.2.dist-info/WHEEL
krane-0.1.2.dist-info/entry_points.txt
krane-0.1.2.dist-info/top_level.txt
krane-0.1.2.dist-info/RECORD
