Metadata-Version: 2.2
Name: krane
Version: 0.1.2
Summary: A light-weight bioinformatics package
Author-email: Callis Ezenwaka <callisezenwaka@outlook.com>
Maintainer-email: Callis Ezenwaka <callisezenwaka@outlook.com>
License:                                Apache License
Project-URL: Homepage, https://github.com/callezenwaka/krane
Project-URL: Documentation, https://krane.readthedocs.io/en/latest/
Project-URL: Repository, https://github.com/callezenwaka/krane.git
Project-URL: Issues, https://github.com/callezenwaka/krane/issues
Project-URL: Changelog, https://github.com/callezenwaka/krane/blob/main/CHANGELOG.md
Keywords: Bioinformatics,python,fastapi,web,Biotech,Genomics
Classifier: Development Status :: 5 - Production/Stable
Classifier: Intended Audience :: Developers
Classifier: Topic :: Software Development :: Build Tools
Classifier: Programming Language :: Python :: 3
Classifier: Programming Language :: Python :: 3.10
Classifier: Operating System :: OS Independent
Requires-Python: >=3.10
License-File: LICENSE
Requires-Dist: fastapi>=0.115.6
Requires-Dist: uvicorn>=0.34.0
Requires-Dist: pydantic>=2.10.3
Requires-Dist: click>=8.1.7
Provides-Extra: test
Requires-Dist: pytest; extra == "test"
Requires-Dist: pytest-cov; extra == "test"
Requires-Dist: pytest-regressions; extra == "test"
Provides-Extra: dev
Requires-Dist: black; extra == "dev"
Requires-Dist: pyyaml; extra == "dev"
Requires-Dist: pre-commit; extra == "dev"
Requires-Dist: tox; extra == "dev"
